sp_lib_light/__init__.py
sp_lib_light/sp_lib_l.py
sp_lib_l-1.0.1.dist-info/METADATA
sp_lib_l-1.0.1.dist-info/WHEEL
sp_lib_l-1.0.1.dist-info/top_level.txt
sp_lib_l-1.0.1.dist-info/RECORD
