Metadata-Version: 2.1
Name: sp_lib_l
Version: 1.0.1
Summary: sp_lib_l: Log OFF/Non wait version
Home-page: https://github.com/greenroomy/amazon_sp_api
Download-URL: https://github.com/greenroomy/amazon_sp_api/
Author: Shinji Uetsuki
Author-email: greenroom1973@gmail.com
Maintainer: Shinji Uetsuki
Maintainer-email: greenroom1973@gmail.com
License: MIT license
Requires-Python: >=3.8
Requires-Dist: requests (>=2.28.2)
Requires-Dist: pandas (>=1.5.3)
Requires-Dist: urllib3 (>=1.26.15)
Requires-Dist: pandas (>=1.2.4)
